Interpreter/__init__.py
Interpreter/__main__.py
Interpreter/connection.py
Interpreter/functions.py
Interpreter/string_subs.py
Interpreter/translate.py
Interpreter/triples_map/TriplesMap.py
Interpreter/triples_map/__init__.py
dragoman_tool-1.1.dev1669825114.dist-info/LICENSE
dragoman_tool-1.1.dev1669825114.dist-info/METADATA
dragoman_tool-1.1.dev1669825114.dist-info/WHEEL
dragoman_tool-1.1.dev1669825114.dist-info/top_level.txt
dragoman_tool-1.1.dev1669825114.dist-info/RECORD
