Metadata-Version: 2.1
Name: dragoman-tool
Version: 1.1.dev1669825114
Summary: An Optimized, RML-engine-agnostic Interpreter for Functional Mappings. It planns the optimized execution of FnO functions integrated in RML mapping rules, interprets and transforms the rules into function-free ones efficiently. Since Dragoman is engine-agnostic it can be adopted by any RML-compliant Knowledge Graph creation framework.
Home-page: https://github.com/SDM-TIB/Dragoman
Author: Samaneh Jozashoori, Enrique Iglesias
Author-email: samaneh.jozashoori@tib.eu, enrique.iglesias@tib.eu
License: Apache 2.0
Platform: UNKNOWN
Classifier: Programming Language :: Python :: 3
Classifier: License :: OSI Approved :: Apache Software License
Classifier: Operating System :: OS Independent
Classifier: Development Status :: 5 - Production/Stable
Classifier: Environment :: Console
Classifier: Intended Audience :: Science/Research
Classifier: Topic :: Utilities
Classifier: Topic :: Software Development :: Pre-processors
Classifier: Topic :: Scientific/Engineering :: Interface Engine/Protocol Translator
Requires-Python: >=3.6
Requires-Dist: flask
Requires-Dist: mysql-connector-python
Requires-Dist: pandas
Requires-Dist: pyparsing (==2.2.0)
Requires-Dist: rdflib (==4.2.2)
Requires-Dist: requests
Requires-Dist: unidecode
